onlineChange/__init__.py
onlineChange/bayes.py
onlineChange/bayes_unknown_pre.py
onlineChange/sim.detect.bayes.unknown.pre.py
onlineChange/stat.py
onlineChange-0.0.6.dist-info/LICENSE.txt
onlineChange-0.0.6.dist-info/METADATA
onlineChange-0.0.6.dist-info/WHEEL
onlineChange-0.0.6.dist-info/top_level.txt
onlineChange-0.0.6.dist-info/RECORD
