Metadata-Version: 2.1
Name: onlineChange
Version: 0.0.6
Summary: Quickest change detection algorithms for online streaming data in python.
Home-page: https://github.com/Yorkee2018/cpd.python
Author: Xiangyu Zhang, Yi Rong, Jie Ding
Author-email: zhan6004@umn.edu, dingj@umn.edu
License: GNU GPLv3
Platform: UNKNOWN
Classifier: Topic :: Education
Classifier: Topic :: Scientific/Engineering :: Information Analysis
Classifier: Topic :: Scientific/Engineering :: Mathematics
Classifier: Topic :: Scientific/Engineering
Classifier: License :: OSI Approved :: GNU General Public License v3 (GPLv3)
Classifier: Programming Language :: Python
Classifier: Programming Language :: Python :: 3.6
Classifier: Programming Language :: Python :: 3.7
Classifier: Programming Language :: Python :: 3.8
Classifier: Intended Audience :: Education
Classifier: Intended Audience :: Developers
Classifier: Intended Audience :: Information Technology
Classifier: Intended Audience :: Science/Research
